<annotation>
	<folder>5</folder>
	<filename>DCNB5RYIF7XL.jpg</filename>
	<path>..\Dataset\5\DCNB5RYIF7XL.jpg</path>
	<source>
		<database>Unknown</database>
	</source>
	<size>
		<width>640</width>
		<height>640</height>
		<depth>3</depth>
	</size>
	<segmented>0</segmented>
	<object>
		<name>hamburger</name>
		<pose>Unspecified</pose>
		<truncated>0</truncated>
		<difficult>0</difficult>
		<bndbox>
			<xmin>49</xmin>
			<ymin>190</ymin>
			<xmax>391</xmax>
			<ymax>418</ymax>
		</bndbox>
	</object>
</annotation>